LICENSE.txt
MANIFEST.in
README.rst
setup.py
pysdl_gpu.egg-info/PKG-INFO
pysdl_gpu.egg-info/SOURCES.txt
pysdl_gpu.egg-info/dependency_links.txt
pysdl_gpu.egg-info/requires.txt
pysdl_gpu.egg-info/top_level.txt
sdlgpu/__init__.py
sdlgpu/sdlgpu.py